LICENSE.txt
README.md
setup.cfg
setup.py
imagetokens/__inti__.py
imagetokens/dataset.py
imagetokens/tokenization.py
imagetokens.egg-info/PKG-INFO
imagetokens.egg-info/SOURCES.txt
imagetokens.egg-info/dependency_links.txt
imagetokens.egg-info/requires.txt
imagetokens.egg-info/top_level.txt