Metadata-Version: 2.1
Name: imagetokens
Version: 0.1
Summary: A lightweight library for image tokenization and dataset loading in PyTorch.
Home-page: https://github.com/Isaac45/Tokenized-Hash.git
Download-URL: https://github.com/Isaac45/Tokenized-Hash.git/archive/v_01.tar.gz
Author: Isaac Adjei-Mensah
Author-email: iadjeimensah@gmail.com
License: MIT
Keywords: image,tokenization,pytorch,dataset,vision
Classifier: Development Status :: 3 - Alpha
Classifier: Intended Audience :: Developers
Classifier: Topic :: Software Development :: Build Tools
Classifier: License :: OSI Approved :: MIT License
Classifier: Programming Language :: Python :: 3.7
Classifier: Programming Language :: Python :: 3.8
Classifier: Programming Language :: Python :: 3.9
Classifier: Programming Language :: Python :: 3.10
Classifier: Programming Language :: Python :: 3.11
License-File: LICENSE.txt
Requires-Dist: torch>=2.1
Requires-Dist: torchvision>=0.16
Requires-Dist: pillow>=10.0
Requires-Dist: python>=3.9
